{
  "$schema": "https://tree-sitter.github.io/tree-sitter/assets/schemas/grammar.schema.json",
  "name": "prime",
  "rules": {
    "program": {
      "type": "SEQ",
      "members": [
        {
          "type": "CHOICE",
          "members": [
            {
              "type": "SYMBOL",
              "name": "module_declaration"
            },
            {
              "type": "BLANK"
            }
          ]
        },
        {
          "type": "REPEAT",
          "content": {
            "type": "SYMBOL",
            "name": "import_declaration"
          }
        },
        {
          "type": "REPEAT",
          "content": {
            "type": "SYMBOL",
            "name": "item"
          }
        }
      ]
    },
    "module_declaration": {
      "type": "SEQ",
      "members": [
        {
          "type": "STRING",
          "value": "module"
        },
        {
          "type": "FIELD",
          "name": "name",
          "content": {
            "type": "SYMBOL",
            "name": "module_path"
          }
        },
        {
          "type": "STRING",
          "value": ";"
        }
      ]
    },
    "import_declaration": {
      "type": "SEQ",
      "members": [
        {
          "type": "CHOICE",
          "members": [
            {
              "type": "STRING",
              "value": "pub"
            },
            {
              "type": "BLANK"
            }
          ]
        },
        {
          "type": "STRING",
          "value": "import"
        },
        {
          "type": "FIELD",
          "name": "path",
          "content": {
            "type": "CHOICE",
            "members": [
              {
                "type": "SYMBOL",
                "name": "module_path"
              },
              {
                "type": "SYMBOL",
                "name": "string_literal"
              }
            ]
          }
        },
        {
          "type": "CHOICE",
          "members": [
            {
              "type": "SEQ",
              "members": [
                {
                  "type": "STRING",
                  "value": "as"
                },
                {
                  "type": "FIELD",
                  "name": "alias",
                  "content": {
                    "type": "SYMBOL",
                    "name": "identifier"
                  }
                }
              ]
            },
            {
              "type": "BLANK"
            }
          ]
        },
        {
          "type": "STRING",
          "value": ";"
        }
      ]
    },
    "module_path": {
      "type": "PREC",
      "value": 1,
      "content": {
        "type": "SEQ",
        "members": [
          {
            "type": "FIELD",
            "name": "head",
            "content": {
              "type": "CHOICE",
              "members": [
                {
                  "type": "SYMBOL",
                  "name": "identifier"
                },
                {
                  "type": "SYMBOL",
                  "name": "type_identifier"
                }
              ]
            }
          },
          {
            "type": "REPEAT",
            "content": {
              "type": "SEQ",
              "members": [
                {
                  "type": "STRING",
                  "value": "::"
                },
                {
                  "type": "FIELD",
                  "name": "tail",
                  "content": {
                    "type": "CHOICE",
                    "members": [
                      {
                        "type": "SYMBOL",
                        "name": "identifier"
                      },
                      {
                        "type": "SYMBOL",
                        "name": "type_identifier"
                      }
                    ]
                  }
                }
              ]
            }
          }
        ]
      }
    },
    "type_path": {
      "type": "SEQ",
      "members": [
        {
          "type": "CHOICE",
          "members": [
            {
              "type": "SEQ",
              "members": [
                {
                  "type": "SYMBOL",
                  "name": "module_path"
                },
                {
                  "type": "STRING",
                  "value": "::"
                }
              ]
            },
            {
              "type": "BLANK"
            }
          ]
        },
        {
          "type": "SYMBOL",
          "name": "type_identifier"
        }
      ]
    },
    "item": {
      "type": "SEQ",
      "members": [
        {
          "type": "CHOICE",
          "members": [
            {
              "type": "STRING",
              "value": "pub"
            },
            {
              "type": "BLANK"
            }
          ]
        },
        {
          "type": "CHOICE",
          "members": [
            {
              "type": "SYMBOL",
              "name": "function_definition"
            },
            {
              "type": "SYMBOL",
              "name": "struct_definition"
            },
            {
              "type": "SYMBOL",
              "name": "enum_definition"
            },
            {
              "type": "SYMBOL",
              "name": "interface_definition"
            },
            {
              "type": "SYMBOL",
              "name": "impl_definition"
            },
            {
              "type": "SYMBOL",
              "name": "const_definition"
            }
          ]
        }
      ]
    },
    "struct_definition": {
      "type": "SEQ",
      "members": [
        {
          "type": "STRING",
          "value": "struct"
        },
        {
          "type": "FIELD",
          "name": "name",
          "content": {
            "type": "SYMBOL",
            "name": "type_identifier"
          }
        },
        {
          "type": "CHOICE",
          "members": [
            {
              "type": "FIELD",
              "name": "type_parameters",
              "content": {
                "type": "SYMBOL",
                "name": "type_parameters"
              }
            },
            {
              "type": "BLANK"
            }
          ]
        },
        {
          "type": "STRING",
          "value": "{"
        },
        {
          "type": "REPEAT",
          "content": {
            "type": "SYMBOL",
            "name": "struct_field"
          }
        },
        {
          "type": "STRING",
          "value": "}"
        }
      ]
    },
    "struct_field": {
      "type": "CHOICE",
      "members": [
        {
          "type": "SEQ",
          "members": [
            {
              "type": "FIELD",
              "name": "name",
              "content": {
                "type": "SYMBOL",
                "name": "identifier"
              }
            },
            {
              "type": "STRING",
              "value": ":"
            },
            {
              "type": "FIELD",
              "name": "type",
              "content": {
                "type": "SYMBOL",
                "name": "type_expression"
              }
            },
            {
              "type": "STRING",
              "value": ";"
            }
          ]
        },
        {
          "type": "SEQ",
          "members": [
            {
              "type": "FIELD",
              "name": "embedded",
              "content": {
                "type": "SYMBOL",
                "name": "type_expression"
              }
            },
            {
              "type": "STRING",
              "value": ";"
            }
          ]
        }
      ]
    },
    "enum_definition": {
      "type": "SEQ",
      "members": [
        {
          "type": "STRING",
          "value": "enum"
        },
        {
          "type": "FIELD",
          "name": "name",
          "content": {
            "type": "SYMBOL",
            "name": "type_identifier"
          }
        },
        {
          "type": "CHOICE",
          "members": [
            {
              "type": "FIELD",
              "name": "type_parameters",
              "content": {
                "type": "SYMBOL",
                "name": "type_parameters"
              }
            },
            {
              "type": "BLANK"
            }
          ]
        },
        {
          "type": "STRING",
          "value": "{"
        },
        {
          "type": "CHOICE",
          "members": [
            {
              "type": "SEQ",
              "members": [
                {
                  "type": "SYMBOL",
                  "name": "enum_variant"
                },
                {
                  "type": "REPEAT",
                  "content": {
                    "type": "SEQ",
                    "members": [
                      {
                        "type": "STRING",
                        "value": ","
                      },
                      {
                        "type": "SYMBOL",
                        "name": "enum_variant"
                      }
                    ]
                  }
                },
                {
                  "type": "CHOICE",
                  "members": [
                    {
                      "type": "STRING",
                      "value": ","
                    },
                    {
                      "type": "BLANK"
                    }
                  ]
                }
              ]
            },
            {
              "type": "BLANK"
            }
          ]
        },
        {
          "type": "STRING",
          "value": "}"
        }
      ]
    },
    "enum_variant": {
      "type": "SEQ",
      "members": [
        {
          "type": "FIELD",
          "name": "name",
          "content": {
            "type": "CHOICE",
            "members": [
              {
                "type": "SYMBOL",
                "name": "identifier"
              },
              {
                "type": "SYMBOL",
                "name": "type_identifier"
              }
            ]
          }
        },
        {
          "type": "CHOICE",
          "members": [
            {
              "type": "SEQ",
              "members": [
                {
                  "type": "STRING",
                  "value": "("
                },
                {
                  "type": "SEQ",
                  "members": [
                    {
                      "type": "SYMBOL",
                      "name": "type_expression"
                    },
                    {
                      "type": "REPEAT",
                      "content": {
                        "type": "SEQ",
                        "members": [
                          {
                            "type": "STRING",
                            "value": ","
                          },
                          {
                            "type": "SYMBOL",
                            "name": "type_expression"
                          }
                        ]
                      }
                    },
                    {
                      "type": "CHOICE",
                      "members": [
                        {
                          "type": "STRING",
                          "value": ","
                        },
                        {
                          "type": "BLANK"
                        }
                      ]
                    }
                  ]
                },
                {
                  "type": "STRING",
                  "value": ")"
                }
              ]
            },
            {
              "type": "BLANK"
            }
          ]
        }
      ]
    },
    "interface_definition": {
      "type": "SEQ",
      "members": [
        {
          "type": "STRING",
          "value": "interface"
        },
        {
          "type": "FIELD",
          "name": "name",
          "content": {
            "type": "SYMBOL",
            "name": "type_identifier"
          }
        },
        {
          "type": "CHOICE",
          "members": [
            {
              "type": "FIELD",
              "name": "type_parameters",
              "content": {
                "type": "SYMBOL",
                "name": "type_parameters"
              }
            },
            {
              "type": "BLANK"
            }
          ]
        },
        {
          "type": "STRING",
          "value": "{"
        },
        {
          "type": "REPEAT",
          "content": {
            "type": "SYMBOL",
            "name": "interface_method"
          }
        },
        {
          "type": "STRING",
          "value": "}"
        }
      ]
    },
    "interface_method": {
      "type": "SEQ",
      "members": [
        {
          "type": "STRING",
          "value": "fn"
        },
        {
          "type": "FIELD",
          "name": "name",
          "content": {
            "type": "SYMBOL",
            "name": "identifier"
          }
        },
        {
          "type": "FIELD",
          "name": "parameters",
          "content": {
            "type": "SYMBOL",
            "name": "parameter_list"
          }
        },
        {
          "type": "CHOICE",
          "members": [
            {
              "type": "FIELD",
              "name": "returns",
              "content": {
                "type": "SYMBOL",
                "name": "return_type"
              }
            },
            {
              "type": "BLANK"
            }
          ]
        },
        {
          "type": "STRING",
          "value": ";"
        }
      ]
    },
    "impl_definition": {
      "type": "SEQ",
      "members": [
        {
          "type": "STRING",
          "value": "impl"
        },
        {
          "type": "FIELD",
          "name": "interface",
          "content": {
            "type": "SYMBOL",
            "name": "type_expression"
          }
        },
        {
          "type": "STRING",
          "value": "for"
        },
        {
          "type": "FIELD",
          "name": "target",
          "content": {
            "type": "SYMBOL",
            "name": "type_expression"
          }
        },
        {
          "type": "STRING",
          "value": "{"
        },
        {
          "type": "REPEAT",
          "content": {
            "type": "SYMBOL",
            "name": "function_definition"
          }
        },
        {
          "type": "STRING",
          "value": "}"
        }
      ]
    },
    "const_definition": {
      "type": "SEQ",
      "members": [
        {
          "type": "STRING",
          "value": "const"
        },
        {
          "type": "FIELD",
          "name": "name",
          "content": {
            "type": "SYMBOL",
            "name": "identifier"
          }
        },
        {
          "type": "CHOICE",
          "members": [
            {
              "type": "SEQ",
              "members": [
                {
                  "type": "STRING",
                  "value": ":"
                },
                {
                  "type": "FIELD",
                  "name": "type",
                  "content": {
                    "type": "SYMBOL",
                    "name": "type_expression"
                  }
                }
              ]
            },
            {
              "type": "BLANK"
            }
          ]
        },
        {
          "type": "STRING",
          "value": "="
        },
        {
          "type": "FIELD",
          "name": "value",
          "content": {
            "type": "SYMBOL",
            "name": "expression"
          }
        },
        {
          "type": "STRING",
          "value": ";"
        }
      ]
    },
    "function_definition": {
      "type": "SEQ",
      "members": [
        {
          "type": "STRING",
          "value": "fn"
        },
        {
          "type": "FIELD",
          "name": "name",
          "content": {
            "type": "SYMBOL",
            "name": "identifier"
          }
        },
        {
          "type": "CHOICE",
          "members": [
            {
              "type": "FIELD",
              "name": "type_parameters",
              "content": {
                "type": "SYMBOL",
                "name": "type_parameters"
              }
            },
            {
              "type": "BLANK"
            }
          ]
        },
        {
          "type": "FIELD",
          "name": "parameters",
          "content": {
            "type": "SYMBOL",
            "name": "parameter_list"
          }
        },
        {
          "type": "CHOICE",
          "members": [
            {
              "type": "FIELD",
              "name": "returns",
              "content": {
                "type": "SYMBOL",
                "name": "return_type"
              }
            },
            {
              "type": "BLANK"
            }
          ]
        },
        {
          "type": "FIELD",
          "name": "body",
          "content": {
            "type": "CHOICE",
            "members": [
              {
                "type": "SYMBOL",
                "name": "block"
              },
              {
                "type": "SYMBOL",
                "name": "expression_body"
              }
            ]
          }
        }
      ]
    },
    "type_parameters": {
      "type": "SEQ",
      "members": [
        {
          "type": "STRING",
          "value": "["
        },
        {
          "type": "SEQ",
          "members": [
            {
              "type": "SYMBOL",
              "name": "identifier"
            },
            {
              "type": "REPEAT",
              "content": {
                "type": "SEQ",
                "members": [
                  {
                    "type": "STRING",
                    "value": ","
                  },
                  {
                    "type": "SYMBOL",
                    "name": "identifier"
                  }
                ]
              }
            },
            {
              "type": "CHOICE",
              "members": [
                {
                  "type": "STRING",
                  "value": ","
                },
                {
                  "type": "BLANK"
                }
              ]
            }
          ]
        },
        {
          "type": "STRING",
          "value": "]"
        }
      ]
    },
    "parameter_list": {
      "type": "SEQ",
      "members": [
        {
          "type": "STRING",
          "value": "("
        },
        {
          "type": "CHOICE",
          "members": [
            {
              "type": "SEQ",
              "members": [
                {
                  "type": "SYMBOL",
                  "name": "parameter"
                },
                {
                  "type": "REPEAT",
                  "content": {
                    "type": "SEQ",
                    "members": [
                      {
                        "type": "STRING",
                        "value": ","
                      },
                      {
                        "type": "SYMBOL",
                        "name": "parameter"
                      }
                    ]
                  }
                },
                {
                  "type": "CHOICE",
                  "members": [
                    {
                      "type": "STRING",
                      "value": ","
                    },
                    {
                      "type": "BLANK"
                    }
                  ]
                }
              ]
            },
            {
              "type": "BLANK"
            }
          ]
        },
        {
          "type": "STRING",
          "value": ")"
        }
      ]
    },
    "parameter": {
      "type": "SEQ",
      "members": [
        {
          "type": "CHOICE",
          "members": [
            {
              "type": "STRING",
              "value": "mut"
            },
            {
              "type": "BLANK"
            }
          ]
        },
        {
          "type": "FIELD",
          "name": "name",
          "content": {
            "type": "SYMBOL",
            "name": "identifier"
          }
        },
        {
          "type": "STRING",
          "value": ":"
        },
        {
          "type": "FIELD",
          "name": "type",
          "content": {
            "type": "SYMBOL",
            "name": "type_expression"
          }
        }
      ]
    },
    "return_type": {
      "type": "SEQ",
      "members": [
        {
          "type": "STRING",
          "value": "->"
        },
        {
          "type": "CHOICE",
          "members": [
            {
              "type": "SYMBOL",
              "name": "type_expression"
            },
            {
              "type": "SEQ",
              "members": [
                {
                  "type": "STRING",
                  "value": "("
                },
                {
                  "type": "SEQ",
                  "members": [
                    {
                      "type": "SYMBOL",
                      "name": "type_expression"
                    },
                    {
                      "type": "REPEAT",
                      "content": {
                        "type": "SEQ",
                        "members": [
                          {
                            "type": "STRING",
                            "value": ","
                          },
                          {
                            "type": "SYMBOL",
                            "name": "type_expression"
                          }
                        ]
                      }
                    },
                    {
                      "type": "CHOICE",
                      "members": [
                        {
                          "type": "STRING",
                          "value": ","
                        },
                        {
                          "type": "BLANK"
                        }
                      ]
                    }
                  ]
                },
                {
                  "type": "STRING",
                  "value": ")"
                }
              ]
            }
          ]
        }
      ]
    },
    "expression_body": {
      "type": "SEQ",
      "members": [
        {
          "type": "STRING",
          "value": "=>"
        },
        {
          "type": "FIELD",
          "name": "value",
          "content": {
            "type": "SYMBOL",
            "name": "expression"
          }
        },
        {
          "type": "STRING",
          "value": ";"
        }
      ]
    },
    "block": {
      "type": "SEQ",
      "members": [
        {
          "type": "STRING",
          "value": "{"
        },
        {
          "type": "REPEAT",
          "content": {
            "type": "SYMBOL",
            "name": "statement"
          }
        },
        {
          "type": "CHOICE",
          "members": [
            {
              "type": "FIELD",
              "name": "tail",
              "content": {
                "type": "SYMBOL",
                "name": "expression"
              }
            },
            {
              "type": "BLANK"
            }
          ]
        },
        {
          "type": "STRING",
          "value": "}"
        }
      ]
    },
    "statement": {
      "type": "CHOICE",
      "members": [
        {
          "type": "SYMBOL",
          "name": "let_statement"
        },
        {
          "type": "SYMBOL",
          "name": "assign_statement"
        },
        {
          "type": "SYMBOL",
          "name": "return_statement"
        },
        {
          "type": "SYMBOL",
          "name": "while_statement"
        },
        {
          "type": "SYMBOL",
          "name": "for_statement"
        },
        {
          "type": "SYMBOL",
          "name": "defer_statement"
        },
        {
          "type": "SYMBOL",
          "name": "break_statement"
        },
        {
          "type": "SYMBOL",
          "name": "continue_statement"
        },
        {
          "type": "SYMBOL",
          "name": "match_expression"
        },
        {
          "type": "SYMBOL",
          "name": "if_expression"
        },
        {
          "type": "SYMBOL",
          "name": "expression_statement"
        },
        {
          "type": "SYMBOL",
          "name": "block"
        }
      ]
    },
    "let_statement": {
      "type": "SEQ",
      "members": [
        {
          "type": "STRING",
          "value": "let"
        },
        {
          "type": "CHOICE",
          "members": [
            {
              "type": "STRING",
              "value": "mut"
            },
            {
              "type": "BLANK"
            }
          ]
        },
        {
          "type": "CHOICE",
          "members": [
            {
              "type": "PREC_DYNAMIC",
              "value": 1,
              "content": {
                "type": "SEQ",
                "members": [
                  {
                    "type": "FIELD",
                    "name": "pattern",
                    "content": {
                      "type": "SYMBOL",
                      "name": "pattern"
                    }
                  },
                  {
                    "type": "CHOICE",
                    "members": [
                      {
                        "type": "SEQ",
                        "members": [
                          {
                            "type": "STRING",
                            "value": ":"
                          },
                          {
                            "type": "FIELD",
                            "name": "annotation",
                            "content": {
                              "type": "SYMBOL",
                              "name": "type_expression"
                            }
                          }
                        ]
                      },
                      {
                        "type": "BLANK"
                      }
                    ]
                  },
                  {
                    "type": "CHOICE",
                    "members": [
                      {
                        "type": "SEQ",
                        "members": [
                          {
                            "type": "STRING",
                            "value": "="
                          },
                          {
                            "type": "FIELD",
                            "name": "value",
                            "content": {
                              "type": "SYMBOL",
                              "name": "expression"
                            }
                          }
                        ]
                      },
                      {
                        "type": "BLANK"
                      }
                    ]
                  }
                ]
              }
            },
            {
              "type": "PREC_DYNAMIC",
              "value": -1,
              "content": {
                "type": "SEQ",
                "members": [
                  {
                    "type": "FIELD",
                    "name": "type",
                    "content": {
                      "type": "SYMBOL",
                      "name": "type_expression"
                    }
                  },
                  {
                    "type": "FIELD",
                    "name": "name",
                    "content": {
                      "type": "SYMBOL",
                      "name": "identifier"
                    }
                  },
                  {
                    "type": "CHOICE",
                    "members": [
                      {
                        "type": "SEQ",
                        "members": [
                          {
                            "type": "STRING",
                            "value": "="
                          },
                          {
                            "type": "FIELD",
                            "name": "value",
                            "content": {
                              "type": "SYMBOL",
                              "name": "expression"
                            }
                          }
                        ]
                      },
                      {
                        "type": "BLANK"
                      }
                    ]
                  }
                ]
              }
            }
          ]
        },
        {
          "type": "STRING",
          "value": ";"
        }
      ]
    },
    "assign_statement": {
      "type": "SEQ",
      "members": [
        {
          "type": "FIELD",
          "name": "target",
          "content": {
            "type": "SYMBOL",
            "name": "expression"
          }
        },
        {
          "type": "STRING",
          "value": "="
        },
        {
          "type": "FIELD",
          "name": "value",
          "content": {
            "type": "SYMBOL",
            "name": "expression"
          }
        },
        {
          "type": "STRING",
          "value": ";"
        }
      ]
    },
    "return_statement": {
      "type": "SEQ",
      "members": [
        {
          "type": "STRING",
          "value": "return"
        },
        {
          "type": "CHOICE",
          "members": [
            {
              "type": "SEQ",
              "members": [
                {
                  "type": "SYMBOL",
                  "name": "expression"
                },
                {
                  "type": "REPEAT",
                  "content": {
                    "type": "SEQ",
                    "members": [
                      {
                        "type": "STRING",
                        "value": ","
                      },
                      {
                        "type": "SYMBOL",
                        "name": "expression"
                      }
                    ]
                  }
                },
                {
                  "type": "CHOICE",
                  "members": [
                    {
                      "type": "STRING",
                      "value": ","
                    },
                    {
                      "type": "BLANK"
                    }
                  ]
                }
              ]
            },
            {
              "type": "BLANK"
            }
          ]
        },
        {
          "type": "STRING",
          "value": ";"
        }
      ]
    },
    "while_statement": {
      "type": "SEQ",
      "members": [
        {
          "type": "STRING",
          "value": "while"
        },
        {
          "type": "FIELD",
          "name": "condition",
          "content": {
            "type": "SYMBOL",
            "name": "_condition"
          }
        },
        {
          "type": "FIELD",
          "name": "body",
          "content": {
            "type": "SYMBOL",
            "name": "block"
          }
        }
      ]
    },
    "for_statement": {
      "type": "SEQ",
      "members": [
        {
          "type": "STRING",
          "value": "for"
        },
        {
          "type": "FIELD",
          "name": "binding",
          "content": {
            "type": "SYMBOL",
            "name": "identifier"
          }
        },
        {
          "type": "STRING",
          "value": "in"
        },
        {
          "type": "FIELD",
          "name": "target",
          "content": {
            "type": "SYMBOL",
            "name": "expression"
          }
        },
        {
          "type": "FIELD",
          "name": "body",
          "content": {
            "type": "SYMBOL",
            "name": "block"
          }
        }
      ]
    },
    "defer_statement": {
      "type": "SEQ",
      "members": [
        {
          "type": "STRING",
          "value": "defer"
        },
        {
          "type": "FIELD",
          "name": "expression",
          "content": {
            "type": "SYMBOL",
            "name": "expression"
          }
        },
        {
          "type": "STRING",
          "value": ";"
        }
      ]
    },
    "break_statement": {
      "type": "SEQ",
      "members": [
        {
          "type": "STRING",
          "value": "break"
        },
        {
          "type": "STRING",
          "value": ";"
        }
      ]
    },
    "continue_statement": {
      "type": "SEQ",
      "members": [
        {
          "type": "STRING",
          "value": "continue"
        },
        {
          "type": "STRING",
          "value": ";"
        }
      ]
    },
    "expression_statement": {
      "type": "SEQ",
      "members": [
        {
          "type": "FIELD",
          "name": "expression",
          "content": {
            "type": "SYMBOL",
            "name": "expression"
          }
        },
        {
          "type": "STRING",
          "value": ";"
        }
      ]
    },
    "expression": {
      "type": "CHOICE",
      "members": [
        {
          "type": "SYMBOL",
          "name": "try_expression"
        },
        {
          "type": "SYMBOL",
          "name": "match_expression"
        },
        {
          "type": "SYMBOL",
          "name": "if_expression"
        },
        {
          "type": "SYMBOL",
          "name": "range_expression"
        },
        {
          "type": "SYMBOL",
          "name": "binary_expression"
        },
        {
          "type": "SYMBOL",
          "name": "unary_expression"
        },
        {
          "type": "SYMBOL",
          "name": "call_expression"
        },
        {
          "type": "SYMBOL",
          "name": "field_expression"
        },
        {
          "type": "SYMBOL",
          "name": "question_expression"
        },
        {
          "type": "SYMBOL",
          "name": "struct_literal"
        },
        {
          "type": "SYMBOL",
          "name": "map_literal"
        },
        {
          "type": "SYMBOL",
          "name": "array_literal"
        },
        {
          "type": "SYMBOL",
          "name": "format_string_literal"
        },
        {
          "type": "SYMBOL",
          "name": "type_identifier"
        },
        {
          "type": "SYMBOL",
          "name": "block"
        },
        {
          "type": "SYMBOL",
          "name": "tuple_expression"
        },
        {
          "type": "SYMBOL",
          "name": "parenthesized_expression"
        },
        {
          "type": "SYMBOL",
          "name": "identifier"
        },
        {
          "type": "SYMBOL",
          "name": "literal"
        }
      ]
    },
    "try_expression": {
      "type": "SEQ",
      "members": [
        {
          "type": "STRING",
          "value": "try"
        },
        {
          "type": "FIELD",
          "name": "body",
          "content": {
            "type": "SYMBOL",
            "name": "block"
          }
        }
      ]
    },
    "match_expression": {
      "type": "SEQ",
      "members": [
        {
          "type": "STRING",
          "value": "match"
        },
        {
          "type": "FIELD",
          "name": "value",
          "content": {
            "type": "SYMBOL",
            "name": "expression"
          }
        },
        {
          "type": "STRING",
          "value": "{"
        },
        {
          "type": "CHOICE",
          "members": [
            {
              "type": "SEQ",
              "members": [
                {
                  "type": "SYMBOL",
                  "name": "match_arm"
                },
                {
                  "type": "REPEAT",
                  "content": {
                    "type": "SEQ",
                    "members": [
                      {
                        "type": "CHOICE",
                        "members": [
                          {
                            "type": "STRING",
                            "value": ","
                          },
                          {
                            "type": "STRING",
                            "value": ";"
                          }
                        ]
                      },
                      {
                        "type": "SYMBOL",
                        "name": "match_arm"
                      }
                    ]
                  }
                },
                {
                  "type": "CHOICE",
                  "members": [
                    {
                      "type": "CHOICE",
                      "members": [
                        {
                          "type": "STRING",
                          "value": ","
                        },
                        {
                          "type": "STRING",
                          "value": ";"
                        }
                      ]
                    },
                    {
                      "type": "BLANK"
                    }
                  ]
                }
              ]
            },
            {
              "type": "BLANK"
            }
          ]
        },
        {
          "type": "STRING",
          "value": "}"
        }
      ]
    },
    "match_arm": {
      "type": "SEQ",
      "members": [
        {
          "type": "FIELD",
          "name": "pattern",
          "content": {
            "type": "SYMBOL",
            "name": "pattern"
          }
        },
        {
          "type": "CHOICE",
          "members": [
            {
              "type": "SEQ",
              "members": [
                {
                  "type": "STRING",
                  "value": "if"
                },
                {
                  "type": "FIELD",
                  "name": "guard",
                  "content": {
                    "type": "SYMBOL",
                    "name": "expression"
                  }
                }
              ]
            },
            {
              "type": "BLANK"
            }
          ]
        },
        {
          "type": "STRING",
          "value": "=>"
        },
        {
          "type": "FIELD",
          "name": "value",
          "content": {
            "type": "SYMBOL",
            "name": "expression"
          }
        }
      ]
    },
    "if_expression": {
      "type": "PREC_RIGHT",
      "value": 0,
      "content": {
        "type": "SEQ",
        "members": [
          {
            "type": "STRING",
            "value": "if"
          },
          {
            "type": "FIELD",
            "name": "condition",
            "content": {
              "type": "SYMBOL",
              "name": "_condition"
            }
          },
          {
            "type": "FIELD",
            "name": "consequence",
            "content": {
              "type": "SYMBOL",
              "name": "block"
            }
          },
          {
            "type": "CHOICE",
            "members": [
              {
                "type": "FIELD",
                "name": "alternative",
                "content": {
                  "type": "SYMBOL",
                  "name": "else_clause"
                }
              },
              {
                "type": "BLANK"
              }
            ]
          }
        ]
      }
    },
    "else_clause": {
      "type": "SEQ",
      "members": [
        {
          "type": "STRING",
          "value": "else"
        },
        {
          "type": "FIELD",
          "name": "value",
          "content": {
            "type": "CHOICE",
            "members": [
              {
                "type": "SYMBOL",
                "name": "block"
              },
              {
                "type": "SYMBOL",
                "name": "if_expression"
              }
            ]
          }
        }
      ]
    },
    "let_condition": {
      "type": "SEQ",
      "members": [
        {
          "type": "STRING",
          "value": "let"
        },
        {
          "type": "FIELD",
          "name": "pattern",
          "content": {
            "type": "SYMBOL",
            "name": "pattern"
          }
        },
        {
          "type": "STRING",
          "value": "="
        },
        {
          "type": "FIELD",
          "name": "value",
          "content": {
            "type": "PREC_LEFT",
            "value": 5,
            "content": {
              "type": "SYMBOL",
              "name": "expression"
            }
          }
        }
      ]
    },
    "_condition": {
      "type": "CHOICE",
      "members": [
        {
          "type": "SYMBOL",
          "name": "let_condition"
        },
        {
          "type": "SYMBOL",
          "name": "expression"
        }
      ]
    },
    "range_expression": {
      "type": "PREC_LEFT",
      "value": 3,
      "content": {
        "type": "SEQ",
        "members": [
          {
            "type": "FIELD",
            "name": "start",
            "content": {
              "type": "SYMBOL",
              "name": "expression"
            }
          },
          {
            "type": "FIELD",
            "name": "operator",
            "content": {
              "type": "CHOICE",
              "members": [
                {
                  "type": "STRING",
                  "value": ".."
                },
                {
                  "type": "STRING",
                  "value": "..="
                }
              ]
            }
          },
          {
            "type": "FIELD",
            "name": "end",
            "content": {
              "type": "SYMBOL",
              "name": "expression"
            }
          }
        ]
      }
    },
    "binary_expression": {
      "type": "CHOICE",
      "members": [
        {
          "type": "PREC_LEFT",
          "value": 4,
          "content": {
            "type": "SEQ",
            "members": [
              {
                "type": "SYMBOL",
                "name": "expression"
              },
              {
                "type": "STRING",
                "value": "||"
              },
              {
                "type": "SYMBOL",
                "name": "expression"
              }
            ]
          }
        },
        {
          "type": "PREC_LEFT",
          "value": 5,
          "content": {
            "type": "SEQ",
            "members": [
              {
                "type": "SYMBOL",
                "name": "expression"
              },
              {
                "type": "STRING",
                "value": "&&"
              },
              {
                "type": "SYMBOL",
                "name": "expression"
              }
            ]
          }
        },
        {
          "type": "PREC_LEFT",
          "value": 6,
          "content": {
            "type": "SEQ",
            "members": [
              {
                "type": "SYMBOL",
                "name": "expression"
              },
              {
                "type": "STRING",
                "value": "|"
              },
              {
                "type": "SYMBOL",
                "name": "expression"
              }
            ]
          }
        },
        {
          "type": "PREC_LEFT",
          "value": 7,
          "content": {
            "type": "SEQ",
            "members": [
              {
                "type": "SYMBOL",
                "name": "expression"
              },
              {
                "type": "STRING",
                "value": "^"
              },
              {
                "type": "SYMBOL",
                "name": "expression"
              }
            ]
          }
        },
        {
          "type": "PREC_LEFT",
          "value": 8,
          "content": {
            "type": "SEQ",
            "members": [
              {
                "type": "SYMBOL",
                "name": "expression"
              },
              {
                "type": "STRING",
                "value": "&"
              },
              {
                "type": "SYMBOL",
                "name": "expression"
              }
            ]
          }
        },
        {
          "type": "PREC_LEFT",
          "value": 9,
          "content": {
            "type": "SEQ",
            "members": [
              {
                "type": "SYMBOL",
                "name": "expression"
              },
              {
                "type": "CHOICE",
                "members": [
                  {
                    "type": "STRING",
                    "value": "=="
                  },
                  {
                    "type": "STRING",
                    "value": "!="
                  }
                ]
              },
              {
                "type": "SYMBOL",
                "name": "expression"
              }
            ]
          }
        },
        {
          "type": "PREC_LEFT",
          "value": 10,
          "content": {
            "type": "SEQ",
            "members": [
              {
                "type": "SYMBOL",
                "name": "expression"
              },
              {
                "type": "CHOICE",
                "members": [
                  {
                    "type": "STRING",
                    "value": "<"
                  },
                  {
                    "type": "STRING",
                    "value": "<="
                  },
                  {
                    "type": "STRING",
                    "value": ">"
                  },
                  {
                    "type": "STRING",
                    "value": ">="
                  }
                ]
              },
              {
                "type": "SYMBOL",
                "name": "expression"
              }
            ]
          }
        },
        {
          "type": "PREC_LEFT",
          "value": 11,
          "content": {
            "type": "SEQ",
            "members": [
              {
                "type": "SYMBOL",
                "name": "expression"
              },
              {
                "type": "CHOICE",
                "members": [
                  {
                    "type": "STRING",
                    "value": "+"
                  },
                  {
                    "type": "STRING",
                    "value": "-"
                  }
                ]
              },
              {
                "type": "SYMBOL",
                "name": "expression"
              }
            ]
          }
        },
        {
          "type": "PREC_LEFT",
          "value": 12,
          "content": {
            "type": "SEQ",
            "members": [
              {
                "type": "SYMBOL",
                "name": "expression"
              },
              {
                "type": "CHOICE",
                "members": [
                  {
                    "type": "STRING",
                    "value": "*"
                  },
                  {
                    "type": "STRING",
                    "value": "/"
                  },
                  {
                    "type": "STRING",
                    "value": "%"
                  }
                ]
              },
              {
                "type": "SYMBOL",
                "name": "expression"
              }
            ]
          }
        }
      ]
    },
    "unary_expression": {
      "type": "PREC_RIGHT",
      "value": 13,
      "content": {
        "type": "CHOICE",
        "members": [
          {
            "type": "SEQ",
            "members": [
              {
                "type": "STRING",
                "value": "-"
              },
              {
                "type": "SYMBOL",
                "name": "expression"
              }
            ]
          },
          {
            "type": "SEQ",
            "members": [
              {
                "type": "STRING",
                "value": "!"
              },
              {
                "type": "SYMBOL",
                "name": "expression"
              }
            ]
          },
          {
            "type": "SEQ",
            "members": [
              {
                "type": "STRING",
                "value": "&"
              },
              {
                "type": "CHOICE",
                "members": [
                  {
                    "type": "STRING",
                    "value": "mut"
                  },
                  {
                    "type": "BLANK"
                  }
                ]
              },
              {
                "type": "SYMBOL",
                "name": "expression"
              }
            ]
          },
          {
            "type": "SEQ",
            "members": [
              {
                "type": "STRING",
                "value": "*"
              },
              {
                "type": "SYMBOL",
                "name": "expression"
              }
            ]
          },
          {
            "type": "SEQ",
            "members": [
              {
                "type": "STRING",
                "value": "move"
              },
              {
                "type": "SYMBOL",
                "name": "expression"
              }
            ]
          }
        ]
      }
    },
    "call_expression": {
      "type": "PREC_LEFT",
      "value": 14,
      "content": {
        "type": "SEQ",
        "members": [
          {
            "type": "FIELD",
            "name": "function",
            "content": {
              "type": "SYMBOL",
              "name": "expression"
            }
          },
          {
            "type": "CHOICE",
            "members": [
              {
                "type": "FIELD",
                "name": "type_arguments",
                "content": {
                  "type": "SYMBOL",
                  "name": "type_arguments"
                }
              },
              {
                "type": "BLANK"
              }
            ]
          },
          {
            "type": "FIELD",
            "name": "arguments",
            "content": {
              "type": "SYMBOL",
              "name": "argument_list"
            }
          }
        ]
      }
    },
    "question_expression": {
      "type": "PREC_LEFT",
      "value": 14,
      "content": {
        "type": "SEQ",
        "members": [
          {
            "type": "FIELD",
            "name": "value",
            "content": {
              "type": "SYMBOL",
              "name": "expression"
            }
          },
          {
            "type": "STRING",
            "value": "?"
          }
        ]
      }
    },
    "argument_list": {
      "type": "SEQ",
      "members": [
        {
          "type": "STRING",
          "value": "("
        },
        {
          "type": "CHOICE",
          "members": [
            {
              "type": "SEQ",
              "members": [
                {
                  "type": "SYMBOL",
                  "name": "expression"
                },
                {
                  "type": "REPEAT",
                  "content": {
                    "type": "SEQ",
                    "members": [
                      {
                        "type": "STRING",
                        "value": ","
                      },
                      {
                        "type": "SYMBOL",
                        "name": "expression"
                      }
                    ]
                  }
                },
                {
                  "type": "CHOICE",
                  "members": [
                    {
                      "type": "STRING",
                      "value": ","
                    },
                    {
                      "type": "BLANK"
                    }
                  ]
                }
              ]
            },
            {
              "type": "BLANK"
            }
          ]
        },
        {
          "type": "STRING",
          "value": ")"
        }
      ]
    },
    "field_expression": {
      "type": "PREC_LEFT",
      "value": 14,
      "content": {
        "type": "SEQ",
        "members": [
          {
            "type": "FIELD",
            "name": "value",
            "content": {
              "type": "SYMBOL",
              "name": "expression"
            }
          },
          {
            "type": "STRING",
            "value": "."
          },
          {
            "type": "FIELD",
            "name": "field",
            "content": {
              "type": "SYMBOL",
              "name": "identifier"
            }
          }
        ]
      }
    },
    "struct_literal": {
      "type": "SEQ",
      "members": [
        {
          "type": "FIELD",
          "name": "type",
          "content": {
            "type": "SYMBOL",
            "name": "type_path"
          }
        },
        {
          "type": "STRING",
          "value": "{"
        },
        {
          "type": "CHOICE",
          "members": [
            {
              "type": "SEQ",
              "members": [
                {
                  "type": "SYMBOL",
                  "name": "struct_literal_field"
                },
                {
                  "type": "REPEAT",
                  "content": {
                    "type": "SEQ",
                    "members": [
                      {
                        "type": "STRING",
                        "value": ","
                      },
                      {
                        "type": "SYMBOL",
                        "name": "struct_literal_field"
                      }
                    ]
                  }
                },
                {
                  "type": "CHOICE",
                  "members": [
                    {
                      "type": "STRING",
                      "value": ","
                    },
                    {
                      "type": "BLANK"
                    }
                  ]
                }
              ]
            },
            {
              "type": "BLANK"
            }
          ]
        },
        {
          "type": "STRING",
          "value": "}"
        }
      ]
    },
    "struct_literal_field": {
      "type": "CHOICE",
      "members": [
        {
          "type": "SEQ",
          "members": [
            {
              "type": "FIELD",
              "name": "name",
              "content": {
                "type": "SYMBOL",
                "name": "identifier"
              }
            },
            {
              "type": "STRING",
              "value": ":"
            },
            {
              "type": "FIELD",
              "name": "value",
              "content": {
                "type": "SYMBOL",
                "name": "expression"
              }
            }
          ]
        },
        {
          "type": "FIELD",
          "name": "value",
          "content": {
            "type": "SYMBOL",
            "name": "expression"
          }
        }
      ]
    },
    "map_literal": {
      "type": "SEQ",
      "members": [
        {
          "type": "STRING",
          "value": "#"
        },
        {
          "type": "STRING",
          "value": "{"
        },
        {
          "type": "CHOICE",
          "members": [
            {
              "type": "SEQ",
              "members": [
                {
                  "type": "SYMBOL",
                  "name": "map_entry"
                },
                {
                  "type": "REPEAT",
                  "content": {
                    "type": "SEQ",
                    "members": [
                      {
                        "type": "STRING",
                        "value": ","
                      },
                      {
                        "type": "SYMBOL",
                        "name": "map_entry"
                      }
                    ]
                  }
                },
                {
                  "type": "CHOICE",
                  "members": [
                    {
                      "type": "STRING",
                      "value": ","
                    },
                    {
                      "type": "BLANK"
                    }
                  ]
                }
              ]
            },
            {
              "type": "BLANK"
            }
          ]
        },
        {
          "type": "STRING",
          "value": "}"
        }
      ]
    },
    "map_entry": {
      "type": "SEQ",
      "members": [
        {
          "type": "FIELD",
          "name": "key",
          "content": {
            "type": "SYMBOL",
            "name": "expression"
          }
        },
        {
          "type": "STRING",
          "value": ":"
        },
        {
          "type": "FIELD",
          "name": "value",
          "content": {
            "type": "SYMBOL",
            "name": "expression"
          }
        }
      ]
    },
    "array_literal": {
      "type": "SEQ",
      "members": [
        {
          "type": "STRING",
          "value": "["
        },
        {
          "type": "CHOICE",
          "members": [
            {
              "type": "SEQ",
              "members": [
                {
                  "type": "SYMBOL",
                  "name": "expression"
                },
                {
                  "type": "REPEAT",
                  "content": {
                    "type": "SEQ",
                    "members": [
                      {
                        "type": "STRING",
                        "value": ","
                      },
                      {
                        "type": "SYMBOL",
                        "name": "expression"
                      }
                    ]
                  }
                },
                {
                  "type": "CHOICE",
                  "members": [
                    {
                      "type": "STRING",
                      "value": ","
                    },
                    {
                      "type": "BLANK"
                    }
                  ]
                }
              ]
            },
            {
              "type": "BLANK"
            }
          ]
        },
        {
          "type": "STRING",
          "value": "]"
        }
      ]
    },
    "tuple_expression": {
      "type": "SEQ",
      "members": [
        {
          "type": "STRING",
          "value": "("
        },
        {
          "type": "CHOICE",
          "members": [
            {
              "type": "SEQ",
              "members": [
                {
                  "type": "SYMBOL",
                  "name": "expression"
                },
                {
                  "type": "STRING",
                  "value": ","
                },
                {
                  "type": "SYMBOL",
                  "name": "expression"
                },
                {
                  "type": "REPEAT",
                  "content": {
                    "type": "SEQ",
                    "members": [
                      {
                        "type": "STRING",
                        "value": ","
                      },
                      {
                        "type": "SYMBOL",
                        "name": "expression"
                      }
                    ]
                  }
                },
                {
                  "type": "CHOICE",
                  "members": [
                    {
                      "type": "STRING",
                      "value": ","
                    },
                    {
                      "type": "BLANK"
                    }
                  ]
                }
              ]
            },
            {
              "type": "SEQ",
              "members": [
                {
                  "type": "SYMBOL",
                  "name": "expression"
                },
                {
                  "type": "STRING",
                  "value": ","
                }
              ]
            }
          ]
        },
        {
          "type": "STRING",
          "value": ")"
        }
      ]
    },
    "format_string_literal": {
      "type": "TOKEN",
      "content": {
        "type": "SEQ",
        "members": [
          {
            "type": "STRING",
            "value": "`"
          },
          {
            "type": "REPEAT",
            "content": {
              "type": "CHOICE",
              "members": [
                {
                  "type": "PATTERN",
                  "value": "[^\\\\`]"
                },
                {
                  "type": "PATTERN",
                  "value": "\\\\."
                }
              ]
            }
          },
          {
            "type": "STRING",
            "value": "`"
          }
        ]
      }
    },
    "parenthesized_expression": {
      "type": "SEQ",
      "members": [
        {
          "type": "STRING",
          "value": "("
        },
        {
          "type": "SYMBOL",
          "name": "expression"
        },
        {
          "type": "STRING",
          "value": ")"
        }
      ]
    },
    "pattern": {
      "type": "CHOICE",
      "members": [
        {
          "type": "STRING",
          "value": "_"
        },
        {
          "type": "SYMBOL",
          "name": "literal"
        },
        {
          "type": "SYMBOL",
          "name": "enum_pattern"
        },
        {
          "type": "SYMBOL",
          "name": "tuple_pattern"
        },
        {
          "type": "SYMBOL",
          "name": "map_pattern"
        },
        {
          "type": "SYMBOL",
          "name": "struct_pattern"
        },
        {
          "type": "SYMBOL",
          "name": "slice_pattern"
        },
        {
          "type": "SYMBOL",
          "name": "identifier"
        }
      ]
    },
    "enum_pattern": {
      "type": "SEQ",
      "members": [
        {
          "type": "CHOICE",
          "members": [
            {
              "type": "SEQ",
              "members": [
                {
                  "type": "FIELD",
                  "name": "enum",
                  "content": {
                    "type": "SYMBOL",
                    "name": "module_path"
                  }
                },
                {
                  "type": "STRING",
                  "value": "::"
                }
              ]
            },
            {
              "type": "BLANK"
            }
          ]
        },
        {
          "type": "FIELD",
          "name": "variant",
          "content": {
            "type": "CHOICE",
            "members": [
              {
                "type": "SYMBOL",
                "name": "identifier"
              },
              {
                "type": "SYMBOL",
                "name": "type_identifier"
              }
            ]
          }
        },
        {
          "type": "CHOICE",
          "members": [
            {
              "type": "SEQ",
              "members": [
                {
                  "type": "STRING",
                  "value": "("
                },
                {
                  "type": "CHOICE",
                  "members": [
                    {
                      "type": "SEQ",
                      "members": [
                        {
                          "type": "SYMBOL",
                          "name": "pattern"
                        },
                        {
                          "type": "REPEAT",
                          "content": {
                            "type": "SEQ",
                            "members": [
                              {
                                "type": "STRING",
                                "value": ","
                              },
                              {
                                "type": "SYMBOL",
                                "name": "pattern"
                              }
                            ]
                          }
                        },
                        {
                          "type": "CHOICE",
                          "members": [
                            {
                              "type": "STRING",
                              "value": ","
                            },
                            {
                              "type": "BLANK"
                            }
                          ]
                        }
                      ]
                    },
                    {
                      "type": "BLANK"
                    }
                  ]
                },
                {
                  "type": "STRING",
                  "value": ")"
                }
              ]
            },
            {
              "type": "BLANK"
            }
          ]
        }
      ]
    },
    "tuple_pattern": {
      "type": "PREC",
      "value": 1,
      "content": {
        "type": "SEQ",
        "members": [
          {
            "type": "STRING",
            "value": "("
          },
          {
            "type": "CHOICE",
            "members": [
              {
                "type": "SEQ",
                "members": [
                  {
                    "type": "SYMBOL",
                    "name": "pattern"
                  },
                  {
                    "type": "REPEAT",
                    "content": {
                      "type": "SEQ",
                      "members": [
                        {
                          "type": "STRING",
                          "value": ","
                        },
                        {
                          "type": "SYMBOL",
                          "name": "pattern"
                        }
                      ]
                    }
                  },
                  {
                    "type": "CHOICE",
                    "members": [
                      {
                        "type": "STRING",
                        "value": ","
                      },
                      {
                        "type": "BLANK"
                      }
                    ]
                  }
                ]
              },
              {
                "type": "BLANK"
              }
            ]
          },
          {
            "type": "STRING",
            "value": ")"
          }
        ]
      }
    },
    "map_pattern": {
      "type": "SEQ",
      "members": [
        {
          "type": "STRING",
          "value": "#"
        },
        {
          "type": "STRING",
          "value": "{"
        },
        {
          "type": "CHOICE",
          "members": [
            {
              "type": "SEQ",
              "members": [
                {
                  "type": "SYMBOL",
                  "name": "map_pattern_entry"
                },
                {
                  "type": "REPEAT",
                  "content": {
                    "type": "SEQ",
                    "members": [
                      {
                        "type": "STRING",
                        "value": ","
                      },
                      {
                        "type": "SYMBOL",
                        "name": "map_pattern_entry"
                      }
                    ]
                  }
                },
                {
                  "type": "CHOICE",
                  "members": [
                    {
                      "type": "STRING",
                      "value": ","
                    },
                    {
                      "type": "BLANK"
                    }
                  ]
                }
              ]
            },
            {
              "type": "BLANK"
            }
          ]
        },
        {
          "type": "STRING",
          "value": "}"
        }
      ]
    },
    "map_pattern_entry": {
      "type": "SEQ",
      "members": [
        {
          "type": "FIELD",
          "name": "key",
          "content": {
            "type": "SYMBOL",
            "name": "string_literal"
          }
        },
        {
          "type": "STRING",
          "value": ":"
        },
        {
          "type": "FIELD",
          "name": "value",
          "content": {
            "type": "SYMBOL",
            "name": "pattern"
          }
        }
      ]
    },
    "struct_pattern": {
      "type": "SEQ",
      "members": [
        {
          "type": "FIELD",
          "name": "type",
          "content": {
            "type": "SYMBOL",
            "name": "module_path"
          }
        },
        {
          "type": "STRING",
          "value": "{"
        },
        {
          "type": "CHOICE",
          "members": [
            {
              "type": "SEQ",
              "members": [
                {
                  "type": "CHOICE",
                  "members": [
                    {
                      "type": "SYMBOL",
                      "name": "struct_pattern_field"
                    },
                    {
                      "type": "STRING",
                      "value": ".."
                    }
                  ]
                },
                {
                  "type": "REPEAT",
                  "content": {
                    "type": "SEQ",
                    "members": [
                      {
                        "type": "STRING",
                        "value": ","
                      },
                      {
                        "type": "CHOICE",
                        "members": [
                          {
                            "type": "SYMBOL",
                            "name": "struct_pattern_field"
                          },
                          {
                            "type": "STRING",
                            "value": ".."
                          }
                        ]
                      }
                    ]
                  }
                },
                {
                  "type": "CHOICE",
                  "members": [
                    {
                      "type": "STRING",
                      "value": ","
                    },
                    {
                      "type": "BLANK"
                    }
                  ]
                }
              ]
            },
            {
              "type": "BLANK"
            }
          ]
        },
        {
          "type": "STRING",
          "value": "}"
        }
      ]
    },
    "struct_pattern_field": {
      "type": "SEQ",
      "members": [
        {
          "type": "FIELD",
          "name": "name",
          "content": {
            "type": "SYMBOL",
            "name": "identifier"
          }
        },
        {
          "type": "CHOICE",
          "members": [
            {
              "type": "SEQ",
              "members": [
                {
                  "type": "STRING",
                  "value": ":"
                },
                {
                  "type": "FIELD",
                  "name": "value",
                  "content": {
                    "type": "SYMBOL",
                    "name": "pattern"
                  }
                }
              ]
            },
            {
              "type": "BLANK"
            }
          ]
        }
      ]
    },
    "slice_pattern": {
      "type": "SEQ",
      "members": [
        {
          "type": "STRING",
          "value": "["
        },
        {
          "type": "CHOICE",
          "members": [
            {
              "type": "SEQ",
              "members": [
                {
                  "type": "CHOICE",
                  "members": [
                    {
                      "type": "SYMBOL",
                      "name": "pattern"
                    },
                    {
                      "type": "SYMBOL",
                      "name": "slice_rest"
                    }
                  ]
                },
                {
                  "type": "REPEAT",
                  "content": {
                    "type": "SEQ",
                    "members": [
                      {
                        "type": "STRING",
                        "value": ","
                      },
                      {
                        "type": "CHOICE",
                        "members": [
                          {
                            "type": "SYMBOL",
                            "name": "pattern"
                          },
                          {
                            "type": "SYMBOL",
                            "name": "slice_rest"
                          }
                        ]
                      }
                    ]
                  }
                },
                {
                  "type": "CHOICE",
                  "members": [
                    {
                      "type": "STRING",
                      "value": ","
                    },
                    {
                      "type": "BLANK"
                    }
                  ]
                }
              ]
            },
            {
              "type": "BLANK"
            }
          ]
        },
        {
          "type": "STRING",
          "value": "]"
        }
      ]
    },
    "slice_rest": {
      "type": "SEQ",
      "members": [
        {
          "type": "STRING",
          "value": ".."
        },
        {
          "type": "CHOICE",
          "members": [
            {
              "type": "SYMBOL",
              "name": "pattern"
            },
            {
              "type": "BLANK"
            }
          ]
        }
      ]
    },
    "literal": {
      "type": "PREC",
      "value": 1,
      "content": {
        "type": "CHOICE",
        "members": [
          {
            "type": "SYMBOL",
            "name": "integer_literal"
          },
          {
            "type": "SYMBOL",
            "name": "float_literal"
          },
          {
            "type": "SYMBOL",
            "name": "string_literal"
          },
          {
            "type": "SYMBOL",
            "name": "rune_literal"
          },
          {
            "type": "SYMBOL",
            "name": "boolean_literal"
          }
        ]
      }
    },
    "boolean_literal": {
      "type": "CHOICE",
      "members": [
        {
          "type": "STRING",
          "value": "true"
        },
        {
          "type": "STRING",
          "value": "false"
        }
      ]
    },
    "integer_literal": {
      "type": "TOKEN",
      "content": {
        "type": "PATTERN",
        "value": "[0-9]+"
      }
    },
    "float_literal": {
      "type": "TOKEN",
      "content": {
        "type": "SEQ",
        "members": [
          {
            "type": "PATTERN",
            "value": "[0-9]+"
          },
          {
            "type": "CHOICE",
            "members": [
              {
                "type": "SEQ",
                "members": [
                  {
                    "type": "STRING",
                    "value": "."
                  },
                  {
                    "type": "PATTERN",
                    "value": "[0-9]+"
                  },
                  {
                    "type": "CHOICE",
                    "members": [
                      {
                        "type": "SEQ",
                        "members": [
                          {
                            "type": "PATTERN",
                            "value": "[eE]"
                          },
                          {
                            "type": "CHOICE",
                            "members": [
                              {
                                "type": "PATTERN",
                                "value": "[+-]"
                              },
                              {
                                "type": "BLANK"
                              }
                            ]
                          },
                          {
                            "type": "PATTERN",
                            "value": "[0-9]+"
                          }
                        ]
                      },
                      {
                        "type": "BLANK"
                      }
                    ]
                  }
                ]
              },
              {
                "type": "SEQ",
                "members": [
                  {
                    "type": "PATTERN",
                    "value": "[eE]"
                  },
                  {
                    "type": "CHOICE",
                    "members": [
                      {
                        "type": "PATTERN",
                        "value": "[+-]"
                      },
                      {
                        "type": "BLANK"
                      }
                    ]
                  },
                  {
                    "type": "PATTERN",
                    "value": "[0-9]+"
                  }
                ]
              }
            ]
          }
        ]
      }
    },
    "string_literal": {
      "type": "TOKEN",
      "content": {
        "type": "SEQ",
        "members": [
          {
            "type": "STRING",
            "value": "\""
          },
          {
            "type": "REPEAT",
            "content": {
              "type": "CHOICE",
              "members": [
                {
                  "type": "PATTERN",
                  "value": "[^\"\\\\]"
                },
                {
                  "type": "PATTERN",
                  "value": "\\\\."
                }
              ]
            }
          },
          {
            "type": "STRING",
            "value": "\""
          }
        ]
      }
    },
    "rune_literal": {
      "type": "TOKEN",
      "content": {
        "type": "SEQ",
        "members": [
          {
            "type": "STRING",
            "value": "'"
          },
          {
            "type": "CHOICE",
            "members": [
              {
                "type": "PATTERN",
                "value": "[^'\\\\]"
              },
              {
                "type": "PATTERN",
                "value": "\\\\."
              }
            ]
          },
          {
            "type": "STRING",
            "value": "'"
          }
        ]
      }
    },
    "type_identifier": {
      "type": "TOKEN",
      "content": {
        "type": "PREC",
        "value": 1,
        "content": {
          "type": "PATTERN",
          "value": "[A-Z][A-Za-z0-9_]*"
        }
      }
    },
    "identifier": {
      "type": "TOKEN",
      "content": {
        "type": "PATTERN",
        "value": "[A-Za-z_][A-Za-z0-9_]*"
      }
    },
    "type_expression": {
      "type": "CHOICE",
      "members": [
        {
          "type": "SYMBOL",
          "name": "pointer_type"
        },
        {
          "type": "SYMBOL",
          "name": "reference_type"
        },
        {
          "type": "SYMBOL",
          "name": "slice_type"
        },
        {
          "type": "SYMBOL",
          "name": "array_type"
        },
        {
          "type": "SYMBOL",
          "name": "tuple_type"
        },
        {
          "type": "SYMBOL",
          "name": "generic_type"
        },
        {
          "type": "SYMBOL",
          "name": "type_path"
        },
        {
          "type": "SYMBOL",
          "name": "type_identifier"
        },
        {
          "type": "SYMBOL",
          "name": "identifier"
        }
      ]
    },
    "pointer_type": {
      "type": "SEQ",
      "members": [
        {
          "type": "STRING",
          "value": "*"
        },
        {
          "type": "CHOICE",
          "members": [
            {
              "type": "STRING",
              "value": "mut"
            },
            {
              "type": "BLANK"
            }
          ]
        },
        {
          "type": "SYMBOL",
          "name": "type_expression"
        }
      ]
    },
    "reference_type": {
      "type": "SEQ",
      "members": [
        {
          "type": "STRING",
          "value": "&"
        },
        {
          "type": "CHOICE",
          "members": [
            {
              "type": "STRING",
              "value": "mut"
            },
            {
              "type": "BLANK"
            }
          ]
        },
        {
          "type": "SYMBOL",
          "name": "type_expression"
        }
      ]
    },
    "slice_type": {
      "type": "SEQ",
      "members": [
        {
          "type": "STRING",
          "value": "["
        },
        {
          "type": "STRING",
          "value": "]"
        },
        {
          "type": "SYMBOL",
          "name": "type_expression"
        }
      ]
    },
    "array_type": {
      "type": "SEQ",
      "members": [
        {
          "type": "STRING",
          "value": "["
        },
        {
          "type": "SYMBOL",
          "name": "integer_literal"
        },
        {
          "type": "STRING",
          "value": "]"
        },
        {
          "type": "SYMBOL",
          "name": "type_expression"
        }
      ]
    },
    "tuple_type": {
      "type": "SEQ",
      "members": [
        {
          "type": "STRING",
          "value": "("
        },
        {
          "type": "SEQ",
          "members": [
            {
              "type": "SYMBOL",
              "name": "type_expression"
            },
            {
              "type": "REPEAT",
              "content": {
                "type": "SEQ",
                "members": [
                  {
                    "type": "STRING",
                    "value": ","
                  },
                  {
                    "type": "SYMBOL",
                    "name": "type_expression"
                  }
                ]
              }
            },
            {
              "type": "CHOICE",
              "members": [
                {
                  "type": "STRING",
                  "value": ","
                },
                {
                  "type": "BLANK"
                }
              ]
            }
          ]
        },
        {
          "type": "STRING",
          "value": ")"
        }
      ]
    },
    "generic_type": {
      "type": "SEQ",
      "members": [
        {
          "type": "FIELD",
          "name": "name",
          "content": {
            "type": "SYMBOL",
            "name": "type_path"
          }
        },
        {
          "type": "STRING",
          "value": "["
        },
        {
          "type": "SEQ",
          "members": [
            {
              "type": "SYMBOL",
              "name": "type_expression"
            },
            {
              "type": "REPEAT",
              "content": {
                "type": "SEQ",
                "members": [
                  {
                    "type": "STRING",
                    "value": ","
                  },
                  {
                    "type": "SYMBOL",
                    "name": "type_expression"
                  }
                ]
              }
            },
            {
              "type": "CHOICE",
              "members": [
                {
                  "type": "STRING",
                  "value": ","
                },
                {
                  "type": "BLANK"
                }
              ]
            }
          ]
        },
        {
          "type": "STRING",
          "value": "]"
        }
      ]
    },
    "type_arguments": {
      "type": "SEQ",
      "members": [
        {
          "type": "STRING",
          "value": "["
        },
        {
          "type": "SEQ",
          "members": [
            {
              "type": "SYMBOL",
              "name": "type_expression"
            },
            {
              "type": "REPEAT",
              "content": {
                "type": "SEQ",
                "members": [
                  {
                    "type": "STRING",
                    "value": ","
                  },
                  {
                    "type": "SYMBOL",
                    "name": "type_expression"
                  }
                ]
              }
            },
            {
              "type": "CHOICE",
              "members": [
                {
                  "type": "STRING",
                  "value": ","
                },
                {
                  "type": "BLANK"
                }
              ]
            }
          ]
        },
        {
          "type": "STRING",
          "value": "]"
        }
      ]
    },
    "comment": {
      "type": "TOKEN",
      "content": {
        "type": "CHOICE",
        "members": [
          {
            "type": "SEQ",
            "members": [
              {
                "type": "STRING",
                "value": "//"
              },
              {
                "type": "PATTERN",
                "value": "[^\\n]*"
              }
            ]
          },
          {
            "type": "SEQ",
            "members": [
              {
                "type": "STRING",
                "value": "/*"
              },
              {
                "type": "PATTERN",
                "value": "[^*]*\\*+([^/*][^*]*\\*+)*"
              },
              {
                "type": "STRING",
                "value": "/"
              }
            ]
          }
        ]
      }
    }
  },
  "extras": [
    {
      "type": "PATTERN",
      "value": "\\s|\\\\\\r?\\n"
    },
    {
      "type": "SYMBOL",
      "name": "comment"
    }
  ],
  "conflicts": [
    [
      "statement",
      "expression"
    ],
    [
      "return_type",
      "tuple_type"
    ],
    [
      "pattern",
      "enum_pattern"
    ],
    [
      "pattern",
      "enum_pattern",
      "type_expression"
    ],
    [
      "type_path",
      "enum_pattern"
    ],
    [
      "type_path",
      "enum_pattern",
      "type_expression"
    ],
    [
      "type_path",
      "expression"
    ],
    [
      "module_path"
    ],
    [
      "type_path",
      "type_expression"
    ]
  ],
  "precedences": [],
  "externals": [],
  "inline": [],
  "supertypes": [
    "statement",
    "expression",
    "literal",
    "type_expression",
    "pattern"
  ],
  "reserved": {}
}